mypt/shortcuts.py
mypt/_data/dataloaders/standard_dataloaders.py
mypt/_data/datasets/genericFolderDs.py
mypt/_data/datasets/obj_detect_loc/abstract_ds.py
mypt/_data/datasets/obj_detect_loc/object_detect_ds.py
mypt/_data/datasets/obj_detect_loc/object_localization.py
mypt/_data/datasets/parallel_augmentation/parallel_aug_abstract.py
mypt/_data/datasets/parallel_augmentation/parallel_aug_dir.py
mypt/_data/datasets/parallel_augmentation/parallel_aug_ds_wrapper.py
mypt/backbones/alexnetFeatureExtractor.py
mypt/backbones/resnetFeatureExtractor.py
mypt/code_utilities/annotation_utilites.py
mypt/code_utilities/directories_and_files.py
mypt/code_utilities/pytorch_utilities.py
mypt/data/dataloaders/standard_dataloaders.py
mypt/data/datasets/genericFolderDs.py
mypt/data/datasets/image_classification/utils.py
mypt/data/datasets/mixins/cls_ds_wrapper.py
mypt/data/datasets/obj_detect_loc/abstract_ds.py
mypt/data/datasets/obj_detect_loc/object_detect_ds.py
mypt/data/datasets/obj_detect_loc/object_localization.py
mypt/data/datasets/parallel_augmentation/parallel_aug_abstract.py
mypt/data/datasets/parallel_augmentation/parallel_aug_dir.py
mypt/data/datasets/parallel_augmentation/parallel_aug_ds_wrapper.py
mypt/dimensions_analysis/dimension_analyser.py
mypt/dimensions_analysis/layer_specific.py
mypt/dimensions_analysis/testing/__init__.py
mypt/dimensions_analysis/testing/test_dimensions_analysis.py
mypt/distances/MMD.py
mypt/distances/euclidean.py
mypt/linearBlocks/classification_head.py
mypt/losses/simClrLoss.py
mypt/losses/object_detection/object_localization.py
mypt/models/object_detection/obj_localization.py
mypt/models/simClr/simClrModel.py
mypt/schedulers/annealing_lr.py
mypt/schedulers/warmup.py
mypt/similarities/cosineSim.py
mypt/subroutines/neighbors/knn.py
mypt/subroutines/neighbors/model_embs.py
mypt-1.1.0.dist-info/METADATA
mypt-1.1.0.dist-info/WHEEL
mypt-1.1.0.dist-info/RECORD
