Metadata-Version: 2.3
Name: mypt
Version: 1.1.0
Summary: A package to train, load and save fully Unsupervised model
Project-URL: Homepage, https://code.university.innopolis.ru/OGTC/%D0%A1%D0%B2%D0%B0%D1%80%D0%BA%D0%B0-%D0%93%D0%A1%D0%9F/_git/weldbook-qa-lib
Author-email: Ayhem Bouabid <a.bouabid@innopolis.university>
Classifier: License :: OSI Approved :: MIT License
Classifier: Operating System :: OS Independent
Classifier: Programming Language :: Python :: 3
Requires-Python: >=3.10
Requires-Dist: mypt
